piroq/__init__.py
piroq/__main__.py
piroq/app.py
piroq/command.py
piroq/service.py
piroq-0.0.2.dist-info/LICENSE.txt
piroq-0.0.2.dist-info/METADATA
piroq-0.0.2.dist-info/WHEEL
piroq-0.0.2.dist-info/entry_points.txt
piroq-0.0.2.dist-info/top_level.txt
piroq-0.0.2.dist-info/RECORD
