Metadata-Version: 2.1
Name: piroq
Version: 0.0.2
Summary: PiroQ: Turns a Raspberry Pi into a Heroku-like execution environment.
Home-page: https://github.com/christophevg/piroq
Author: Christophe VG
License: MIT
Keywords: framework cloud raspberrypi procfile
Platform: UNKNOWN
Classifier: Environment :: Console
Classifier: Development Status :: 4 - Beta
Classifier: Intended Audience :: Developers
Classifier: Intended Audience :: System Administrators
Classifier: Topic :: Software Development
Classifier: License :: OSI Approved :: MIT License
Classifier: Programming Language :: Python
Classifier: Programming Language :: Python :: 2.7
Classifier: Programming Language :: Python :: 3.7
Requires-Dist: python-dotenv
Requires-Dist: servicefactory
Requires-Dist: procfile-manager
Requires-Dist: GitPython
